langchain_scrapingbee/__init__.py
langchain_scrapingbee/py.typed
langchain_scrapingbee/tools.py
langchain_scrapingbee-0.2.0.dist-info/METADATA
langchain_scrapingbee-0.2.0.dist-info/WHEEL
langchain_scrapingbee-0.2.0.dist-info/licenses/LICENSE
langchain_scrapingbee-0.2.0.dist-info/RECORD
