Metadata-Version: 2.4
Name: langchain-scrapingbee
Version: 0.2.0
Summary: An integration package connecting Scrapingbee and LangChain
License: MIT
License-File: LICENSE
Requires-Python: >=3.9,<4.0
Classifier: License :: OSI Approved :: MIT License
Classifier: Programming Language :: Python :: 3
Classifier: Programming Language :: Python :: 3.9
Classifier: Programming Language :: Python :: 3.10
Classifier: Programming Language :: Python :: 3.11
Classifier: Programming Language :: Python :: 3.12
Classifier: Programming Language :: Python :: 3.13
Classifier: Programming Language :: Python :: 3.14
Requires-Dist: langchain (>=0.3.27,<0.4.0)
Requires-Dist: langchain-core (>=0.3.15,<0.4.0)
Project-URL: Repository, https://github.com/ScrapingBee/langchain-scrapingbee
Project-URL: Release Notes, https://github.com/ScrapingBee/langchain-scrapingbee/blob/master/release_notes.md
Project-URL: Source Code, https://github.com/ScrapingBee/langchain-scrapingbee/blob/master/langchain_scrapingbee/tools.py
